TaskTower/BaseCase.py
TaskTower/BaseType.py
TaskTower/CaseLayer.py
TaskTower/FeatureLayer.py
TaskTower/ProjectLayer.py
TaskTower/Step.py
TaskTower/StepLayer.py
TaskTower/__init__.py
TaskTower-1.0.dist-info/LICENSE
TaskTower-1.0.dist-info/METADATA
TaskTower-1.0.dist-info/WHEEL
TaskTower-1.0.dist-info/top_level.txt
TaskTower-1.0.dist-info/RECORD
