Metadata-Version: 2.1
Name: TaskTower
Version: 1.0
Summary: TaskTower （任务塔）一个任务执行与状态监控装载器
Home-page: https://gitee.com/go9sky/TaskTower.git
Author: go9sky
Author-email: toptobest@163.com
License: MIT
Requires-Python: >=3.6
License-File: LICENSE
Requires-Dist: lxml
Requires-Dist: pydantic
